casm/bset/__init__.py
casm/bset/__main__.py
casm/bset/_helpers.py
casm/bset/_methods.py
casm/bset/json_io.py
casm/bset/misc.py
casm/bset/parsing.py
casm/bset/clexwriter/__init__.py
casm/bset/clexwriter/_cpp_str.py
casm/bset/clexwriter/_methods.py
casm/bset/clexwriter/_write_v1_basic.py
casm/bset/cluster_functions/__init__.py
casm/bset/cluster_functions/_basis_function_specs.py
casm/bset/cluster_functions/_clex_basis_specs.py
casm/bset/cluster_functions/_cluster_functions.py
casm/bset/cluster_functions/_discrete_functions.py
casm/bset/cluster_functions/_matrix_rep.py
casm/bset/cluster_functions/_misc.py
casm/bset/polynomial_functions/__init__.py
casm/bset/polynomial_functions/_polynomial_function.py
casm/bset/templates/base.cpp
casm/bset/templates/v1.basic/Clexulator.cpp
casm/bset/templates/v1.basic/clexulator_constructor_def.cpp
casm/bset/templates/v1.basic/clexulator_private_decl.cpp
casm/bset/templates/v1.basic/clexulator_private_def.cpp
casm_bset-2.1.0.dist-info/licenses/LICENSE
casm_bset-2.1.0.dist-info/METADATA
casm_bset-2.1.0.dist-info/WHEEL
casm_bset-2.1.0.dist-info/top_level.txt
casm_bset-2.1.0.dist-info/RECORD
