Metadata-Version: 2.4
Name: casm-bset
Version: 2.1.0
Summary: CASM cluster expansion basis set generation
Author-email: CASM developers <casm-developers@lists.engr.ucsb.edu>
License-Expression: LGPL-2.1-or-later
Project-URL: Homepage, https://prisms-center.github.io/CASMcode_docs/
Project-URL: Repository, https://github.com/prisms-center/CASMcode_bset
Classifier: Development Status :: 5 - Production/Stable
Classifier: Programming Language :: Python :: 3
Classifier: Topic :: Scientific/Engineering
Requires-Python: <3.14,>=3.9
License-File: LICENSE
Requires-Dist: jinja2
Requires-Dist: libcasm-configuration>=2.0.0
Requires-Dist: numpy
Requires-Dist: opt-einsum
Requires-Dist: scipy
Requires-Dist: sortedcontainers
Requires-Dist: sparse
Dynamic: license-file
